ism/ISM.py
ism/__init__.py
ism/core/__init__.py
ism/core/action_check_timers.py
ism/core/action_confirm_ready_to_run.py
ism/core/action_confirm_ready_to_stop.py
ism/core/action_emergency_shutdown.py
ism/core/action_normal_shutdown.py
ism/core/base_action.py
ism/core/data.json
ism/core/schema.json
ism/dal/__init__.py
ism/dal/mysql_dao.py
ism/dal/sqlite3_dao.py
ism/exceptions/__init__.py
ism/exceptions/exceptions.py
ism/interfaces/__init__.py
ism/interfaces/action_interface.py
ism/interfaces/dao_interface.py
ism/tests/__init__.py
ism/tests/test_ism.py
ism/tests/support/__init__.py
ism/tests/support/action_before_test_support.py
ism/tests/support/action_inbound_test_msg.py
ism/tests/support/action_outbound_test_msg.py
ism/tests/support/action_run_sql_query.py
ism/tests/support/data.json
ism/tests/support/schema.json
ism/tests/test_import_action_pack/__init__.py
ism/tests/test_import_action_pack/action_test_startup.py
ism/tests/test_import_action_pack/data.json
ism/tests/test_import_action_pack/schema.json
ism/tests/test_timer_action/__init__.py
infinite_state_machine-0.1.1.dist-info/LICENSE
infinite_state_machine-0.1.1.dist-info/METADATA
infinite_state_machine-0.1.1.dist-info/WHEEL
infinite_state_machine-0.1.1.dist-info/top_level.txt
infinite_state_machine-0.1.1.dist-info/RECORD
