Metadata-Version: 2.1
Name: infinite-state-machine
Version: 0.1.1
Summary: An Infinite State Machine
Home-page: https://github.com/kaliklipper/python-state-machine
Author: kaliklipper
Author-email: kaliklipper@gmail.com
License: UNKNOWN
Platform: UNKNOWN
Classifier: Programming Language :: Python :: 3
Classifier: License :: OSI Approved :: MIT License
Classifier: Operating System :: OS Independent
Requires-Python: >=3.7
